syringe_pump/__init__.py
syringe_pump/exceptions.py
syringe_pump/pump.py
syringe_pump/rate.py
syringe_pump/response_parser.py
syringe_pump/serial_interface.py
syringe_pump/syringe.py
syringe_pump/time.py
syringe_pump/volume.py
python_syringe_pump-0.2.1.dist-info/LICENSE.md
python_syringe_pump-0.2.1.dist-info/METADATA
python_syringe_pump-0.2.1.dist-info/WHEEL
python_syringe_pump-0.2.1.dist-info/RECORD
