Metadata-Version: 2.1
Name: python-syringe-pump
Version: 0.2.1
Summary: A python controller for syringe pumps, e.g. Legato 100
Home-page: https://github.com/Ddedalus/syringe-pump
License: GPLv3
Author: Hubert Bereś
Author-email: h.beres@hotmail.com
Requires-Python: >=3.10,<4.0
Classifier: License :: Other/Proprietary License
Classifier: Programming Language :: Python :: 3
Classifier: Programming Language :: Python :: 3.10
Classifier: Programming Language :: Python :: 3.11
Requires-Dist: aioserial (>=1.3.1,<2.0.0)
Requires-Dist: pydantic (>=2.0.0,<3.0.0)
Requires-Dist: quantiphy (>=2.19,<3.0)
Project-URL: Repository, https://github.com/Ddedalus/syringe-pump
